Workbook
Name aporte: INVEST!$D$27
Name patrimonio: INVEST!$D$30
Name preco_atual_cota: INVEST!$D$17
Name preco_sobre_valor_patrimonial: INVEST!$D$21
Name qtd_anos: INVEST!$D$28
Name rendimento_carteira: INVEST!$D$13
Name salario: INVEST!$D$12
Name sugestao_investimento: INVEST!$D$14
Name taxa_mensal: INVEST!$D$29
Name ultimo_dividendo: INVEST!$D$19
Name valor_medio_cota: INVEST!$D$20
Name valor_patrimonial_acao: INVEST!$D$18

Sheet INVEST
B11: INFORMAÇÕES INICIAIS
B12: Salário | D12: 3000
B13: Rendimento Carteira | D13: 0.006
B14: Sugestão de Investimento (30%) | D14: =salario*30% -> 900
B16: INFORMAÇÕES IMPORTANTES PARA DECIDIR ALOCAÇÃO
B17: Preço atual da cota | D17: 165
B18: Valor patrimonial por ação | D18: 158
B19: Último rendimento (dividendo) pago por cota | D19: 1.1
B20: Quanto você pagou em média por cota? | D20: 160
B21: P/VP (Preço sobre Valor Patrimonial) | D21: =preco_atual_cota/valor_patrimonial_acao -> 1.0443038
B22: Está com desconto ou está sendo negociado com ágio (caro)? | D22: =IF(preco_sobre_valor_patrimonial<1,"Desconto","Caro") -> Caro
B23: Número Mágico (Cotas para Autossustentabilidade) | D23: =ROUNDUP(preco_atual_cota/ultimo_dividendo,0) -> 150
B24: Yield on Cost (YoC) | D24: =ultimo_dividendo/valor_medio_cota -> 0.006875
B26: INVESTIMENTO MENSAL
B27: Quanto investir por mês? | D27: 200
B28: Por quantos anos? | D28: 2
B29: Qual a taxa de rendimento mensal? | D29: 0.01079
B30: Patrimônio acumulado? | D30: =FV(taxa_mensal,qtd_anos*12,aporte*-1) -> 5445.5255
B31: Dividendos mensais? | D31: =patrimonio*rendimento_carteira -> 32.673153
B33: CENÁRIOS
D34: Dividendo
A35: 2 | B35: Quanto em 2 anos? | C35: =FV(taxa_mensal,$A35*12,aporte*-1) -> 5445.5255 | D35: =C35*rendimento_carteira -> 32.673153
A36: 5 | B36: Quanto em 5 anos? | C36: =FV(taxa_mensal,$A36*12,aporte*-1) -> 16755.383 | D36: =C36*rendimento_carteira -> 100.5323
A37: 10 | B37: Quanto em 10 anos? | C37: =FV(taxa_mensal,$A37*12,aporte*-1) -> 48656.843 | D37: =C37*rendimento_carteira -> 291.94106
A38: 20 | B38: Quanto em 20 anos? | C38: =FV(taxa_mensal,$A38*12,aporte*-1) -> 225039.68 | D38: =C38*rendimento_carteira -> 1350.2381
A39: 30 | B39: Quanto em 30 anos? | C39: =FV(taxa_mensal,$A39*12,aporte*-1) -> 864433.93 | D39: =C39*rendimento_carteira -> 5186.6036
B41: PERFIL | D41: Agressivo
B42: VALOR A SER INVESTIDO POR MÊS | D42: =aporte -> 200
B44: TIPO DE FII | C44: Percentual sugerido | D44: Valores
B45: PAPEL | C45: =VLOOKUP($D$41&"-"&$B45,'Percentual por Perfil'!B2:E20,4,FALSE) -> 0.5 | D45: =C45*$D$42 -> 100
B46: TIJOLO | C46: =VLOOKUP($D$41&"-"&$B46,'Percentual por Perfil'!B3:E21,4,FALSE) -> 0.1 | D46: =C46*$D$42 -> 20
B47: HÍBRIDOS | C47: =VLOOKUP($D$41&"-"&$B47,'Percentual por Perfil'!B4:E22,4,FALSE) -> 0.05 | D47: =C47*$D$42 -> 10
B48: FOFs | C48: =VLOOKUP($D$41&"-"&$B48,'Percentual por Perfil'!B5:E23,4,FALSE) -> 0.05 | D48: =C48*$D$42 -> 10
B49: DESENVOLVIMENTO | C49: =VLOOKUP($D$41&"-"&$B49,'Percentual por Perfil'!B6:E24,4,FALSE) -> 0.2 | D49: =C49*$D$42 -> 40
B50: HOTELARIAS | C50: =VLOOKUP($D$41&"-"&$B50,'Percentual por Perfil'!B7:E25,4,FALSE) -> 0.1 | D50: =C50*$D$42 -> 20
D51: =SUM(D45:D50) -> 200

Sheet Percentual por Perfil
B2: CHAVE | C2: PERFIL | D2: TIPO DE FII | E2: %
B3: =C3&"-"&D3 -> Conservador-PAPEL | C3: Conservador | D3: PAPEL | E3: 0.3
B4: =C4&"-"&D4 -> Conservador-TIJOLO | C4: Conservador | D4: TIJOLO | E4: 0.5 | H4: Escolha o perfil/tipo:
B5: =C5&"-"&D5 -> Conservador-HÍBRIDOS | C5: Conservador | D5: HÍBRIDOS | E5: 0.1 | H5: Conservador-HÍBRIDOS | I5: =VLOOKUP(H5,B2:E20,4,FALSE) -> 0.1
B6: =C6&"-"&D6 -> Conservador-FOFs | C6: Conservador | D6: FOFs | E6: 0.1
B7: =C7&"-"&D7 -> Conservador-DESENVOLVIMENTO | C7: Conservador | D7: DESENVOLVIMENTO | E7: 0
B8: =C8&"-"&D8 -> Conservador-HOTELARIAS | C8: Conservador | D8: HOTELARIAS | E8: 0
B9: =C9&"-"&D9 -> Moderado-PAPEL | C9: Moderado | D9: PAPEL | E9: 0.32
B10: =C10&"-"&D10 -> Moderado-TIJOLO | C10: Moderado | D10: TIJOLO | E10: 0.35
B11: =C11&"-"&D11 -> Moderado-HÍBRIDOS | C11: Moderado | D11: HÍBRIDOS | E11: 0.08
B12: =C12&"-"&D12 -> Moderado-FOFs | C12: Moderado | D12: FOFs | E12: 0.05
B13: =C13&"-"&D13 -> Moderado-DESENVOLVIMENTO | C13: Moderado | D13: DESENVOLVIMENTO | E13: 0.1
B14: =C14&"-"&D14 -> Moderado-HOTELARIAS | C14: Moderado | D14: HOTELARIAS | E14: 0.1
B15: =C15&"-"&D15 -> Agressivo-PAPEL | C15: Agressivo | D15: PAPEL | E15: 0.5
B16: =C16&"-"&D16 -> Agressivo-TIJOLO | C16: Agressivo | D16: TIJOLO | E16: 0.1
B17: =C17&"-"&D17 -> Agressivo-HÍBRIDOS | C17: Agressivo | D17: HÍBRIDOS | E17: 0.05
... B20: =C20&"-"&D20 -> Agressivo-HOTELARIAS | C20: Agressivo | D20: HOTELARIAS | E20: 0.1

Sheet Perguntas de Negócio
B2: Perguntas de negócio para criar um simulador simples de investimento:
B4: Quanto investir por mês?
B6: Por quantos anos?
B8: Taxa de rendimento mensal?
B10: Quanto de patrimônio acumulado terei?
B12: Quanto são os dividendos mensais?
